bbug_dynamics/__init__.py
bbug_dynamics/accounts.py
bbug_dynamics/appointments.py
bbug_dynamics/bbug.py
bbug_dynamics/dynamics.py
bbug_dynamics/settings.py
bbug_dynamics/tasks.py
bbug_dynamics-0.1.1.dist-info/DESCRIPTION.rst
bbug_dynamics-0.1.1.dist-info/METADATA
bbug_dynamics-0.1.1.dist-info/RECORD
bbug_dynamics-0.1.1.dist-info/WHEEL
bbug_dynamics-0.1.1.dist-info/metadata.json
bbug_dynamics-0.1.1.dist-info/top_level.txt
