Metadata-Version: 2.0
Name: bbug-dynamics
Version: 0.1.1
Summary: Bookingbug Dynamics CRM Integration
Home-page: https://github.com/diegopiccinini/bbug_dynamics.git
Author: Diego Piccinini Lagos
Author-email: dlagos@bookingbug.com
License: MIT
Platform: UNKNOWN
